eventstoredb-0.9.0.dist-info/METADATA
eventstoredb-0.9.0.dist-info/WHEEL
eventstoredb-0.9.0.dist-info/licenses/LICENSE
eventstoredb/__init__.py
eventstoredb/__version__.py
eventstoredb/client/__init__.py
eventstoredb/client/append_to_stream/__init__.py
eventstoredb/client/append_to_stream/exceptions.py
eventstoredb/client/append_to_stream/grpc.py
eventstoredb/client/append_to_stream/mixin.py
eventstoredb/client/append_to_stream/types.py
eventstoredb/client/client.py
eventstoredb/client/create_persistent_subscription_to_all/__init__.py
eventstoredb/client/create_persistent_subscription_to_all/grpc.py
eventstoredb/client/create_persistent_subscription_to_all/mixin.py
eventstoredb/client/create_persistent_subscription_to_all/types.py
eventstoredb/client/create_persistent_subscription_to_stream/__init__.py
eventstoredb/client/create_persistent_subscription_to_stream/exceptions.py
eventstoredb/client/create_persistent_subscription_to_stream/grpc.py
eventstoredb/client/create_persistent_subscription_to_stream/mixin.py
eventstoredb/client/create_persistent_subscription_to_stream/types.py
eventstoredb/client/delete_persistent_subscription_to_all/__init__.py
eventstoredb/client/delete_persistent_subscription_to_all/grpc.py
eventstoredb/client/delete_persistent_subscription_to_all/mixin.py
eventstoredb/client/delete_persistent_subscription_to_all/types.py
eventstoredb/client/delete_persistent_subscription_to_stream/__init__.py
eventstoredb/client/delete_persistent_subscription_to_stream/grpc.py
eventstoredb/client/delete_persistent_subscription_to_stream/mixin.py
eventstoredb/client/delete_persistent_subscription_to_stream/types.py
eventstoredb/client/exceptions.py
eventstoredb/client/get_persistent_subscription_details/__init__.py
eventstoredb/client/get_persistent_subscription_details/grpc.py
eventstoredb/client/get_persistent_subscription_details/mixin.py
eventstoredb/client/get_persistent_subscription_details/types.py
eventstoredb/client/protocol.py
eventstoredb/client/read_all/__init__.py
eventstoredb/client/read_all/grpc.py
eventstoredb/client/read_all/mixin.py
eventstoredb-0.9.0.dist-info/RECORD
