Metadata-Version: 2.1
Name: eventstoredb
Version: 0.9.0
Summary: A EventstoreDB gRPC client written in python .
Keywords: eventstore,eventstoredb
Author-Email: betaboon <betaboon@0x80.ninja>
Maintainer-Email: betaboon <betaboon@0x80.ninja>
License: Apache-2.0
Classifier: Development Status :: 4 - Beta
Classifier: Intended Audience :: Developers
Classifier: License :: OSI Approved :: Apache Software License
Classifier: Natural Language :: English
Classifier: Operating System :: OS Independent
Classifier: Programming Language :: Python
Classifier: Programming Language :: Python :: 3
Classifier: Programming Language :: Python :: 3 :: Only
Classifier: Programming Language :: Python :: 3.9
Classifier: Programming Language :: Python :: 3.10
Classifier: Programming Language :: Python :: 3.11
Classifier: Programming Language :: Python :: 3.12
Classifier: Typing :: Typed
Project-URL: Homepage, https://github.com/betaboon/EventStoreDB-Client-Python
Project-URL: Documentation, https://betaboon.github.io/EventStoreDB-Client-Python
Project-URL: Changelog, https://github.com/betaboon/EventStoreDB-Client-Python/releases
Project-URL: Repository, https://github.com/betaboon/EventStoreDB-Client-Python
Project-URL: Issue tracker, https://github.com/betaboon/EventStoreDB-Client-Python/issues
Requires-Python: <3.13,>=3.9
Requires-Dist: betterproto==2.0.0b5
Requires-Dist: yarl>=1.9.4
